candk/__init__.py
candk/candk.py
candk/corndog.py
candk/ketchup/__init__.py
candk/ketchup/base.py
candk/ketchup/main.py
candk/ketchup/spread.py
candk/ketchup/style.css
candk/ketchup/tags.py
candk-2.6.1.dist-info/LICENSE
candk-2.6.1.dist-info/METADATA
candk-2.6.1.dist-info/WHEEL
candk-2.6.1.dist-info/entry_points.txt
candk-2.6.1.dist-info/RECORD
